{
  "00-introduction": {
    "docPath": "docs/00-introduction.md",
    "repos": {
      "cr-api": [],
      "cr-data": []
    },
    "description": "Top-level overview — no single source file; changes whenever any major subsystem changes"
  },
  "backend/01-architecture": {
    "docPath": "docs/backend/01-architecture.md",
    "repos": {
      "cr-api": [
        "Convenience/CR.REST.AIO/Program.cs",
        "Common/CR.Common.Data.Interface/**/*.cs",
        "Common/CR.Common.Data.Postgres/**/*.cs",
        "Common/CR.Common.Data.Sqlite/**/*.cs",
        "Common/CR.Common.REST.Server/**/*.cs"
      ],
      "cr-data": []
    },
    "description": "Backend layer diagram, DDD module structure, dual-DB pattern, DI wiring"
  },
  "backend/02-npc-system": {
    "docPath": "docs/backend/02-npc-system.md",
    "repos": {
      "cr-api": [
        "Npcs/**/*.cs",
        "Npcs/**/*.csproj"
      ],
      "cr-data": [
        "Assets/Scripts/Npcs/**/*NpcCreatureGrantBehaviour*.cs",
        "Assets/Scripts/Npcs/**/*NpcTrainerBehaviour*.cs",
        "Assets/Scripts/Npcs/**/*NpcMerchantBehaviour*.cs",
        "Assets/Scripts/Npcs/**/*INpcSubInitializable*.cs"
      ]
    },
    "description": "NPC CRUD, team management, domain service, REST endpoints, NpcCreatureSlotSpec"
  },
  "backend/03-spawner-system": {
    "docPath": "docs/backend/03-spawner-system.md",
    "repos": {
      "cr-api": [
        "Spawner/**/*.cs",
        "Spawner/**/*.csproj"
      ],
      "cr-data": []
    },
    "description": "Weighted spawn pools, spawn history, spawner tables"
  },
  "backend/04-creature-generation": {
    "docPath": "docs/backend/04-creature-generation.md",
    "repos": {
      "cr-api": [
        "Creatures/**/*.cs",
        "Game/CR.Game.CreatureGeneration/**/*.cs",
        "Game/CR.Game.Domain.Services/**/*.cs"
      ],
      "cr-data": []
    },
    "description": "Creature generation pipeline, growth profiles, abilities assignment"
  },
  "backend/05-starter-creature-flow": {
    "docPath": "docs/backend/05-starter-creature-flow.md",
    "repos": {
      "cr-api": [
        "Npcs/CR.Npcs.Domain.Services/**/*.cs",
        "Trainers/**/*.cs",
        "Game/CR.Game.Domain.Services/**/*.cs"
      ],
      "cr-data": [
        "Assets/Scripts/Npcs/**/*.cs",
        "Assets/Scripts/Trainers/**/*.cs"
      ]
    },
    "description": "Starter creature selection and onboarding flow, end-to-end"
  },
  "backend/06-auth-and-accounts": {
    "docPath": "docs/backend/06-auth-and-accounts.md",
    "repos": {
      "cr-api": [
        "Auth/**/*.cs",
        "Auth/**/*.csproj"
      ],
      "cr-data": [
        "Assets/Scripts/Auth/**/*.cs"
      ]
    },
    "description": "Auth system: JWT, OAuth linking, account management"
  },
  "backend/07-quest-system": {
    "docPath": "docs/backend/07-quest-system.md",
    "repos": {
      "cr-api": [
        "Quests/**/*.cs",
        "Quests/**/*.csproj"
      ],
      "cr-data": [
        "My project/Assets/CR/Quests/**/*.cs"
      ]
    },
    "description": "Quest system: templates, objectives, rewards, instances, progress events, requirements, condition evaluation"
  },
  "backend/08-stats-system": {
    "docPath": "docs/backend/08-stats-system.md",
    "repos": {
      "cr-api": [
        "Stats/**/*.cs",
        "Stats/**/*.csproj"
      ],
      "cr-data": [
        "My project/Assets/CR/Stats/**/*.cs"
      ]
    },
    "description": "CR.Stats lifetime stat tracking domain: trainer_stat, stat_event, operators, StatKey constants"
  },
  "unity/01-project-setup": {
    "docPath": "docs/unity/01-project-setup.md",
    "repos": {
      "cr-api": [],
      "cr-data": [
        "Packages/manifest.json",
        "ProjectSettings/**",
        "Assets/Scripts/Installers/**/*.cs"
      ]
    },
    "description": "Unity project structure, packages, folder layout"
  },
  "unity/02-dependency-injection": {
    "docPath": "docs/unity/02-dependency-injection.md",
    "repos": {
      "cr-api": [],
      "cr-data": [
        "Assets/Scripts/Installers/**/*.cs",
        "Assets/Scripts/**/*Installer*.cs"
      ]
    },
    "description": "Zenject DI patterns, WithId bindings, scene installers"
  },
  "unity/03-world-behaviours": {
    "docPath": "docs/unity/03-world-behaviours.md",
    "repos": {
      "cr-api": [],
      "cr-data": [
        "Assets/Scripts/World/**/*.cs",
        "Assets/Scripts/**/*WorldBehaviour*.cs",
        "Assets/Scripts/**/*WorldInitializ*.cs",
        "Assets/Scripts/**/*GameInitializ*.cs",
        "Assets/Scripts/**/*NpcCreatureGrantBehaviour*.cs",
        "Assets/Scripts/**/*NpcMerchantBehaviour*.cs",
        "Assets/Scripts/**/*NpcTrainerBehaviour*.cs",
        "Assets/Scripts/**/*INpcSubInitializable*.cs"
      ]
    },
    "description": "IWorldInitializable, WorldRegistry, GameInitializer bootstrap, INpcSubInitializable composable NPC sub-behaviours"
  },
  "unity/04-npc-interaction": {
    "docPath": "docs/unity/04-npc-interaction.md",
    "repos": {
      "cr-api": [
        "Npcs/CR.Npcs.Service.REST/**/*.cs"
      ],
      "cr-data": [
        "Assets/Scripts/Npcs/**/*.cs",
        "Assets/Scripts/**/*NpcInteractionBehaviour*.cs",
        "Assets/Scripts/**/*NpcBattleRequest*.cs",
        "Assets/Scripts/**/*NpcCreatureGrantBehaviour*.cs",
        "Assets/Scripts/**/*NpcTrainerBehaviour*.cs",
        "Assets/Scripts/**/*NpcMerchantBehaviour*.cs"
      ]
    },
    "description": "Composable NPC interaction: NpcInteractionBehaviour dispatch, NpcBattleRequest, OnBattleRequested event, grant vs battle flow"
  },
  "unity/05-http-clients": {
    "docPath": "docs/unity/05-http-clients.md",
    "repos": {
      "cr-api": [],
      "cr-data": [
        "Assets/Scripts/**/*HttpClient*.cs",
        "Assets/Scripts/**/*SqliteRepository*.cs",
        "Assets/Scripts/Data/**/*.cs"
      ]
    },
    "description": "Online/offline repository pattern, Best HTTP, SQLite cache"
  },
  "unity/06-localization": {
    "docPath": "docs/unity/06-localization.md",
    "repos": {
      "cr-api": [
        "Game/CR.Game.Localization/LocalizationRepository.cs",
        "Game/CR.Game.Localization/LocalizedText.cs"
      ],
      "cr-data": [
        "My project/Assets/CR/Core/Data/Repository/Implementation/GameCore/LocalizationRepository.cs",
        "My project/Assets/CR/Resources/configuration/localization/*.yaml"
      ]
    },
    "description": "Per-domain per-language YAML localization files, LocalizationRepository loading, key naming convention"
  },
  "unity/07-battle-system": {
    "docPath": "docs/unity/07-battle-system.md",
    "repos": {
      "cr-api": [
        "Game/CR.Game.Service.BFF/Endpoints/BattleEndpoints.cs",
        "Game/CR.Game.Service.BFF/Endpoints/WildBattleEndpoints.cs"
      ],
      "cr-data": [
        "My project/Assets/CR/Game/Battle/BattleCoordinator.cs",
        "My project/Assets/CR/Game/Battle/IBattleClient.cs",
        "My project/Assets/CR/Game/Battle/IBattleCoordinator.cs",
        "My project/Assets/CR/Game/Battle/BattleClientUnityHttp.cs",
        "My project/Assets/CR/Game/Battle/BattleSession.cs",
        "My project/Assets/CR/Game/Battle/WildBattleRequest.cs",
        "My project/Assets/CR/Game/Battle/BattleAnimationConfig.cs",
        "My project/Assets/CR/Game/Battle/Arena/BattleArena.cs",
        "My project/Assets/CR/Game/Battle/Arena/BattleArenaRegistry.cs",
        "My project/Assets/CR/Game/Battle/Arena/BattleCameraController.cs",
        "My project/Assets/CR/Game/Battle/Events/BattleEvents.cs",
        "My project/Assets/CR/Game/Battle/AI/IWildBattleAIService.cs",
        "My project/Assets/CR/Game/Battle/AI/LocalWildBattleAIService.cs",
        "My project/Assets/CR/Game/Battle/DTOs/ActionOutcomeResponse.cs",
        "My project/Assets/CR/Game/Battle/DTOs/SubmitActionRequest.cs",
        "My project/Assets/CR/Game/Battle/DTOs/WildBattleStateDtos.cs",
        "My project/Assets/CR/UI/Battle/BattleHUD.cs",
        "My project/Assets/CR/Game/World/Behaviours/NpcInteractionBehaviour.cs",
        "My project/Assets/CR/Game/World/Behaviours/SpawnerEncounterBehaviour.cs",
        "My project/Assets/CR/Game/World/Behaviours/SpawnerWorldBehaviour.cs"
      ]
    },
    "description": "BattleCoordinator sequential turn loop, IBattleClient HTTP flow, BattleEvents static events, Arena system, BattleHUD, wild AI, StartNpcBattle/StartWildBattle, SpawnerEncounterBehaviour with encounter delay"
  },
  "unity/08-content-registry": {
    "docPath": "docs/unity/08-content-registry.md",
    "repos": {
      "cr-api": [
        "Creatures/CR.Creatures.Data.Migration/M1015EnforceContentKeyNotNullAndUnique.cs",
        "Npcs/CR.Npcs.Data.Migration/M2006EnforceContentKeyNotNullOnNpcs.cs",
        "Spawner/CR.Spawner.Data.Migration/M5012EnforceContentKeyNotNullOnSpawner.cs",
        "Game/CR.Game.Model/Creatures/BaseCreature.cs"
      ],
      "cr-data": [
        "My project/Assets/CR/Core/Data/Registry/IGameContentRegistry.cs",
        "My project/Assets/CR/Core/Data/Registry/ScriptableObjectContentRegistry.cs",
        "My project/Assets/CR/Core/Data/Registry/ServerContentRegistry.cs",
        "My project/Assets/CR/Core/Data/Registry/MutableContentRegistry.cs",
        "My project/Assets/CR/Core/Data/Registry/ContentRegistryInitializer.cs",
        "My project/Assets/CR/Core/Data/Registry/OnlineOfflineContentRegistry.cs",
        "My project/Assets/CR/Core/Data/Registry/ContentRegistryBootstrapper.cs",
        "My project/Assets/CR/Core/Data/Registry/AddressablesCatalogUpdater.cs",
        "My project/Assets/CR/Core/Data/Registry/ContentDefinitionProvider.cs",
        "My project/Assets/CR/Core/Data/Registry/ContentKeys.cs",
        "My project/Assets/CR/Core/Data/Registry/CreatureContentDef.cs",
        "My project/Assets/CR/Core/Data/Registry/ItemContentDef.cs",
        "My project/Assets/CR/Core/Data/Registry/NpcContentDef.cs",
        "My project/Assets/CR/Core/Data/Registry/SpawnerContentDef.cs",
        "My project/Assets/CR/Core/Data/Registry/Definitions/CreatureDefinition.cs",
        "My project/Assets/CR/Core/Data/Registry/Definitions/ItemDefinition.cs",
        "My project/Assets/CR/Core/Data/Registry/Definitions/NpcDefinition.cs",
        "My project/Assets/CR/Core/Data/Registry/Definitions/SpawnerDefinition.cs",
        "My project/Assets/CR/Core/Data/Repository/GameConfigurationKeys.cs",
        "My project/Assets/CR/Core/Data/Repository/Implementation/Config/IContentManifestRepository.cs",
        "My project/Assets/CR/Core/Data/Repository/Implementation/Config/ContentManifestClientUnityHttp.cs",
        "My project/Assets/CR/Core/Data/Repository/Implementation/Config/ContentManifestResponse.cs",
        "My project/Assets/CR/Core/Assets/IGameAssetLoader.cs",
        "My project/Assets/CR/Core/Assets/GameAssetLoader.cs",
        "My project/Assets/CR/Core/Data/Editor/ContentCreatorTool.cs",
        "My project/Assets/CR/Core/Data/Editor/DefinitionEditorExtensions.cs",
        "My project/Assets/CR/Core/Data/Editor/CreatureDefinitionEditor.cs",
        "My project/Assets/CR/Core/Data/Editor/ItemDefinitionEditor.cs",
        "My project/Assets/CR/Core/Data/Editor/NpcDefinitionEditor.cs",
        "My project/Assets/CR/Core/Data/Editor/SpawnerDefinitionEditor.cs",
        "My project/Assets/CR/Core/Data/Editor/ContentDefinitionProviderEditor.cs",
        "My project/Assets/CR/Core/Data/Editor/LocalizationEditorCache.cs",
        "My project/Assets/CR/Core/Data/Editor/LocalizationKeyField.cs",
        "My project/Assets/CR/Core/Data/Editor/LocalizationEditorWindow.cs",
        "My project/Assets/CR/Core/Data/Editor/ContentAuditTool.cs",
        "My project/Assets/CR/Core/Data/Editor/ContentPublishTool.cs"
      ]
    },
    "description": "IGameContentRegistry, ScriptableObjectContentRegistry, ServerContentRegistry, MutableContentRegistry, ContentRegistryInitializer, ContentManifestClientUnityHttp, ContentDefinitionProvider, ContentKeys constants, CreatureDefinition/ItemDefinition/NpcDefinition/SpawnerDefinition ScriptableObjects, CreatureContentDef/ItemContentDef/NpcContentDef/SpawnerContentDef POCOs, IGameAssetLoader.LoadAssetByKeyAsync, ContentCreatorTool EditorWindow, custom Inspectors for all definition types, AddressablesCatalogUpdater, LocalizationEditorWindow, ContentAuditTool, ContentPublishTool"
  },
  "backend/10-asset-management": {
    "docPath": "docs/backend/10-asset-management.md",
    "repos": {
      "cr-api": [
        "Game/CR.Game.Data.Migration/M8005CreateAppConfigTable.cs",
        "Game/CR.Game.Model/Config/AppConfig.cs",
        "Game/CR.Game.Data/Interface/IAppConfigRepository.cs",
        "Game/CR.Game.Data/Implementation/BaseAppConfigRepository.cs",
        "Game/CR.Game.Data.Sqlite/AppConfigRepository.cs",
        "Game/CR.Game.Data.Postgres/AppConfigRepository.cs",
        "Game/CR.Game.Service.BFF/Endpoints/VersionCheckEndpoints.cs",
        "Game/CR.Game.Service.BFF/Endpoints/GameAssetEndpoints.cs",
        "Game/CR.Game.Service.BFF/Endpoints/ContentPublishEndpoints.cs",
        "Game/CR.Game.Domain.Services/Implementation/Asset/AssetDomainService.cs",
        "Game/CR.Game.Data/Interface/IGameAssetRepository.cs",
        "Game/CR.Game.Data/Implementation/BaseGameAssetRepository.cs",
        "Game/CR.Game.Model/Content/ContentManifestResponse.cs",
        "Game/CR.Game.Data/Interface/IContentManifestRepository.cs",
        "Game/CR.Game.Data/Implementation/BaseContentManifestRepository.cs",
        "Game/CR.Game.Data.Postgres/ContentManifestRepository.cs",
        "Game/CR.Game.Data.Sqlite/ContentManifestRepository.cs",
        "Game/CR.Game.Service.BFF/Endpoints/ContentManifestEndpoints.cs",
        "Game/CR.Game.Model/Items/BaseItem.cs",
        "Items/CR.Items.Data.Migration/M6004AddContentKeyToItem.cs"
      ],
      "cr-data": [
        "My project/Assets/CR/Core/Data/Repository/Implementation/Config/IVersionCheckRepository.cs",
        "My project/Assets/CR/Core/Data/Repository/Implementation/Config/VersionCheckClientUnityHttp.cs",
        "My project/Assets/CR/Core/Data/Repository/Implementation/Config/VersionCheckResponse.cs",
        "My project/Assets/CR/Core/Data/Repository/Implementation/Config/IContentManifestRepository.cs",
        "My project/Assets/CR/Core/Data/Repository/Implementation/Config/ContentManifestClientUnityHttp.cs",
        "My project/Assets/CR/Core/Data/Repository/Implementation/Config/ContentManifestResponse.cs",
        "My project/Assets/CR/Core/Data/Editor/ContentPublishTool.cs",
        "My project/Assets/CR/Core/Data/Editor/ContentDeployTool.cs",
        "scripts/setup-s3-bucket.sh",
        "scripts/setup-minio-bucket.sh",
        "scripts/deploy-content.sh"
      ]
    },
    "description": "game_assets table, app_config singleton row, version-check endpoint, content-publish endpoint, content-manifest endpoint, X-Pipeline-Key auth, three-system asset architecture (Addressables CDN, cr-api backend, local SQLite), S3/MinIO CDN setup, deploy scripts"
  },
  "unity/09-addressables-setup": {
    "docPath": "docs/unity/09-addressables-setup.md",
    "repos": {
      "cr-api": [],
      "cr-data": [
        "My project/Assets/CR/Core/Assets/GameAssetLoader.cs",
        "My project/Assets/CR/Core/Assets/IGameAssetLoader.cs",
        "My project/Assets/CR/Core/Player/CreatureSpawner.cs",
        "My project/Assets/CR/Core/Data/Editor/ContentPublishTool.cs",
        "My project/Assets/CR/Core/Data/Editor/ContentDeployTool.cs",
        "scripts/deploy-content.sh",
        "scripts/setup-minio-bucket.sh"
      ]
    },
    "description": "Unity Addressables end-to-end setup: Groups/Profiles windows, Play Mode Script, making assets Addressable, ContentPublishTool Seed to SQLite, Deploy Content tool, MinIO/S3 gotchas, CreatureSpawner MonoBehaviour"
  },
  "backend/09-battle-persistence": {
    "docPath": "docs/backend/09-battle-persistence.md",
    "repos": {
      "cr-api": [
        "Game/CR.Game.Data.Migration/M8004CreateBattleTables.cs",
        "Game/CR.Game.Data.Migration/M8006AddActiveTurnToBattleRound.cs",
        "Game/CR.Game.Data/Interface/IBattleRepository.cs",
        "Game/CR.Game.Data/Implementation/BaseBattleRepository.cs",
        "Game/CR.Game.Data.Postgres/BattleRepository.cs",
        "Game/CR.Game.Data.Sqlite/BattleRepository.cs",
        "Game/CR.Game.Model/Battle/**/*.cs",
        "Game/CR.Game.Domain.Services/Interfaces/Battle/IBattleDomainService.cs",
        "Game/CR.Game.Domain.Services/Interfaces/Battle/IWildBattleAIDomainService.cs",
        "Game/CR.Game.Domain.Services/Implementation/Battle/BattleDomainService.cs",
        "Game/CR.Game.Domain.Services/Implementation/Battle/WildBattleAIDomainService.cs",
        "Game/CR.Game.Service.BFF/Endpoints/BattleEndpoints.cs",
        "Game/CR.Game.Service.BFF/Endpoints/WildBattleEndpoints.cs",
        "Convenience/CR.Game.Compat/Battle/**/*.cs",
        "Convenience/CR.REST.AIO/Program.cs"
      ],
      "cr-data": [
        "My project/Assets/CR/Game/Battle/IBattleClient.cs",
        "My project/Assets/CR/Game/Battle/BattleClientUnityHttp.cs"
      ]
    },
    "description": "Battle DB tables (battle, battle_round, battle_round_input, battle_creature_state, battle_action_log), IBattleRepository, BattleDomainService, REST endpoints, DI wiring"
  }
}
